pylolzapi/__init__.py
pylolzapi/api/base.py
pylolzapi/api/sync.py
pylolzapi/types/categories.py
pylolzapi/types/items.py
pylolzapi/types/payment.py
pylolzapi/types/scope.py
pylolzapi/types/user.py
pylolzapi/utils/exceptions.py
pylolzapi-0.0.2.dist-info/METADATA
pylolzapi-0.0.2.dist-info/WHEEL
pylolzapi-0.0.2.dist-info/top_level.txt
pylolzapi-0.0.2.dist-info/RECORD
