Metadata-Version: 2.1
Name: pylolzapi
Version: 0.0.2
Summary: Python Wrapper for lolz.guru API
Author: urlykkz
Author-email: padreyonez@gmail.com
Classifier: Programming Language :: Python :: 3
Classifier: License :: OSI Approved :: MIT License
Classifier: Operating System :: OS Independent
Requires-Python: >=3.6
Requires-Dist: requests (~=2.28.1)
Requires-Dist: DateTime (~=4.7)
Requires-Dist: pydantic (~=1.9.1)
